README.md
setup.cfg
setup.py
distributions_udacity/Binomialdistribution.py
distributions_udacity/Gaussiandistribution.py
distributions_udacity/Generaldistribution.py
distributions_udacity/__init__.py
yet_another_distributions_udacity.egg-info/PKG-INFO
yet_another_distributions_udacity.egg-info/SOURCES.txt
yet_another_distributions_udacity.egg-info/dependency_links.txt
yet_another_distributions_udacity.egg-info/not-zip-safe
yet_another_distributions_udacity.egg-info/top_level.txt