Metadata-Version: 1.0
Name: yet-another-distributions-udacity
Version: 0.1
Summary: Gaussian distributions exercise for Udacity ML Engineering Nanodegree
Home-page: UNKNOWN
Author: UNKNOWN
Author-email: UNKNOWN
License: UNKNOWN
Platform: UNKNOWN
